qarl/__init__.py
qarl/__main__.py
qarl/_paths.py
qarl/boxes.py
qarl-0.1.1.data/scripts/qarl
qarl-0.1.1.dist-info/LICENSE
qarl-0.1.1.dist-info/METADATA
qarl-0.1.1.dist-info/WHEEL
qarl-0.1.1.dist-info/top_level.txt
qarl-0.1.1.dist-info/RECORD
